{
  "$schema": "https://developer.microsoft.com/json-schemas/spfx/client-side-web-part-manifest.schema.json",
  "id": "1174de0f-ee91-48ae-b3a3-f29e8faf1956",
  "alias": "TripShareWebPart",
  "componentType": "WebPart",

  
  "version": "*",
  "manifestVersion": 2,

  
  
   
  "requiresCustomScript": false,
  "supportedHosts": ["SharePointWebPart", "TeamsPersonalApp", "TeamsTab", "SharePointFullPage"],
  "supportsThemeVariants": true,

  "preconfiguredEntries": [{
    "groupId": "5c03119e-3074-46fd-976b-c60198311f70", 
    "group": { "default": "Advanced" },
    "title": { "default": "TripShare" },
    "description": { "default": "TripShare description" },
    "officeFabricIconFontName": "Page",
    "properties": {
      "description// If true, the component can only be installed on sites where Custom Script is allowed.": "TripShare"
    }
  }]
}
